stocktracer/__init__.py
stocktracer/__main__.py
stocktracer/analysis/__init__.py
stocktracer/analysis/annual_reports.py
stocktracer/analysis/diluted_eps.py
stocktracer/analysis/f_score.py
stocktracer/analysis/stub.py
stocktracer/analysis/tensorflow.py
stocktracer/cache.py
stocktracer/cli.py
stocktracer/collector/__init__.py
stocktracer/collector/sec.py
stocktracer/filter.py
stocktracer/interface.py
stocktracer-0.4.0.dist-info/LICENSE
stocktracer-0.4.0.dist-info/METADATA
stocktracer-0.4.0.dist-info/WHEEL
stocktracer-0.4.0.dist-info/entry_points.txt
stocktracer-0.4.0.dist-info/RECORD
