Metadata-Version: 2.1
Name: stocktracer
Version: 0.4.0
Summary: Tools for aggregating efficient ways to consume and process publically traded equities on the US stock market. Includes support for SEC quarterly data processing.
Home-page: https://github.com/gyund/fundamental-analysis/
Keywords: sec-tools,fundamental analysis,stocks
Author: Gary Yund
Author-email: gyund@users.noreply.github.com
Requires-Python: >=3.10,<3.12
Classifier: Development Status :: 2 - Pre-Alpha
Classifier: Intended Audience :: Science/Research
Classifier: License :: OSI Approved :: Eclipse Public License 2.0 (EPL-2.0)
Classifier: Operating System :: OS Independent
Classifier: Programming Language :: Python :: 3
Classifier: Programming Language :: Python :: 3.10
Classifier: Programming Language :: Python :: 3.11
Classifier: Topic :: Office/Business :: Financial :: Investment
Classifier: Topic :: Scientific/Engineering :: Information Analysis
Provides-Extra: tensorflow
Requires-Dist: alive-progress (>=3.1.3,<3.2.0)
Requires-Dist: beartype (>=0.14.0,<0.15.0)
Requires-Dist: diskcache (>=5.6.1,<5.7.0)
Requires-Dist: fire (>=0.5.0,<0.6.0)
Requires-Dist: pandas (>=2.0.1,<2.1.0)
Requires-Dist: platformdirs (>=3.5.1,<3.6.0)
Requires-Dist: python-dateutil (>=2.8.2,<2.9.0)
Requires-Dist: requests (>=2.31.0,<2.32.0)
Requires-Dist: requests-cache (>=1.0.1,<1.1.0)
Requires-Dist: tabulate (>=0.9.0,<0.10.0)
Requires-Dist: tensorflow-decision-forests (>=1.3.0,<2.0.0) ; extra == "tensorflow"
Project-URL: Bug Tracker, https://github.com/gyund/fundamental-analysis/issues
Project-URL: Documentation, https://gyund.github.io/fundamental-analysis/
Project-URL: Repository, https://github.com/gyund/fundamental-analysis/
